{
  "realm": "cncf-demo",
  "enabled": true,
  "registrationAllowed": false,
  "resetPasswordAllowed": false,
  "sslRequired": "external",
  "identityProviders": [
    {
      "alias": "id-jag",
      "displayName": "ID-JAG Issuer",
      "providerId": "keycloak-oidc",
      "enabled": true,
      "trustEmail": true,
      "storeToken": false,
      "addReadTokenRoleOnCreate": false,
      "config": {
        "issuer": "http://idjag-issuer:9000",
        "authorizationUrl": "http://idjag-issuer:9000/auth",
        "tokenUrl": "http://idjag-issuer:9000/token",
        "jwksUrl": "http://idjag-issuer:9000/jwks",
        "useJwksUrl": "true",
        "clientId": "idjag-receiver",
        "clientSecret": "demo-idjag-secret-change-me",
        "jwtAuthorizationGrantEnabled": "true",
        "jwtAuthorizationGrantAssertionReuseAllowed": "false",
        "jwtAuthorizationGrantMaxAllowedAssertionExpiration": "300"
      }
    }
  ],
  "clients": [
    {
      "clientId": "requesting-app",
      "name": "Requesting App",
      "description": "Requesting application. Signs the user in and initiates cross-app access to the Receiving App.",
      "enabled": true,
      "publicClient": false,
      "secret": "demo-requesting-secret-change-me",
      "standardFlowEnabled": true,
      "directAccessGrantsEnabled": true,
      "serviceAccountsEnabled": true,
      "redirectUris": ["http://localhost:8080/callback", "*"],
      "webOrigins": ["+"],
      "attributes": {
        "standard.token.exchange.enabled": "true",
        "post.logout.redirect.uris": "+"
      }
    },
    {
      "clientId": "receiving-app",
      "name": "Receiving App (ID-JAG receiver)",
      "description": "Receiving application. Exchanges an incoming ID-JAG assertion (jwt-bearer grant) for a local access token, then calls Gitea with it.",
      "enabled": true,
      "publicClient": false,
      "secret": "demo-receiving-secret-change-me",
      "serviceAccountsEnabled": true,
      "consentRequired": false,
      "attributes": {
        "oauth2.jwt.authorization.grant.enabled": "true",
        "oauth2.jwt.authorization.grant.idp": "id-jag"
      }
    }
  ],
  "users": [
    {
      "username": "user",
      "email": "user@example.com",
      "firstName": "Demo",
      "lastName": "User",
      "enabled": true,
      "emailVerified": true,
      "credentials": [
        { "type": "password", "value": "demo-password-change-me", "temporary": false }
      ],
      "federatedIdentities": [
        { "identityProvider": "id-jag", "userId": "user@example.com", "userName": "user" }
      ]
    }
  ]
}
